clean_print/__init__.py
clean_print/clean.py
clean_print_utils-1.0.0.dist-info/LICENSE
clean_print_utils-1.0.0.dist-info/METADATA
clean_print_utils-1.0.0.dist-info/WHEEL
clean_print_utils-1.0.0.dist-info/top_level.txt
clean_print_utils-1.0.0.dist-info/RECORD
